CHANGELOG.md
LICENSE.txt
MANIFEST.in
README.rst
setup.py
infogram/__init__.py
infogram/exceptions.py
infogram/infogram_api.py
infogram.egg-info/PKG-INFO
infogram.egg-info/SOURCES.txt
infogram.egg-info/dependency_links.txt
infogram.egg-info/requires.txt
infogram.egg-info/top_level.txt